rellu/__init__.py
rellu/labels.py
rellu/releasenotes.py
rellu/repo.py
rellu/tasks.py
rellu/version.py
rellu-2.0.1.dist-info/LICENSE.txt
rellu-2.0.1.dist-info/METADATA
rellu-2.0.1.dist-info/WHEEL
rellu-2.0.1.dist-info/top_level.txt
rellu-2.0.1.dist-info/RECORD
