Metadata-Version: 2.1
Name: rellu
Version: 2.0.1
Summary: Tooling to ease creating releases
Home-page: https://github.com/robotframework/rellu
Download-URL: https://pypi.python.org/pypi/rellu
Author: Pekka Klärck and contributors
Author-email: robotframework@gmail.com
License: Apache License 2.0
Keywords: releasing
Platform: any
Classifier: Development Status :: 4 - Beta
Classifier: License :: OSI Approved :: Apache Software License
Classifier: Operating System :: OS Independent
Classifier: Programming Language :: Python :: 3.6
Classifier: Intended Audience :: Developers
Classifier: Topic :: Software Development :: Build Tools
License-File: LICENSE.txt
Requires-Dist: invoke >=2.00
Requires-Dist: PyGithub >=2.00
